zetic/__init__.py
zetic/__main__.py
zetic/cli.py
zetic/client.py
zetic/commands/__init__.py
zetic/commands/auth/__init__.py
zetic/commands/auth/login.py
zetic/commands/auth/logout.py
zetic/commands/gen.py
zetic/config.py
zetic/constants.py
zetic/utils/__init__.py
zetic/utils/filesystem.py
zetic-0.1.7.dist-info/LICENSE
zetic-0.1.7.dist-info/METADATA
zetic-0.1.7.dist-info/WHEEL
zetic-0.1.7.dist-info/entry_points.txt
zetic-0.1.7.dist-info/RECORD
